mkmsdk/MKMClient.py
mkmsdk/MKMOAuth1.py
mkmsdk/__init__.py
mkmsdk/api.py
mkmsdk/api_map.py
mkmsdk/exceptions.py
mkmsdk/mkm.py
mkmsdk/resolvers.py
mkmsdk/serializer.py
mkmsdk/utils.py
mkmsdk-0.6.0.dist-info/LICENSE
mkmsdk-0.6.0.dist-info/METADATA
mkmsdk-0.6.0.dist-info/WHEEL
mkmsdk-0.6.0.dist-info/top_level.txt
mkmsdk-0.6.0.dist-info/RECORD
