Metadata-Version: 2.1
Name: mkmsdk
Version: 0.6.0
Summary: MagicKardMarket sdk
Home-page: https://github.com/silvanocerza/mkm-sdk
Author: Silvano Cerza
License: MIT
Keywords: mkm magickardmarket magiccardmarket sdk mtg magic the gathering card market rest tcg trading card game pokemon wow world of warcraft yugioh
Classifier: Development Status :: 5 - Production/Stable
Classifier: License :: OSI Approved :: MIT License
Classifier: Intended Audience :: Developers
Classifier: Natural Language :: English
Classifier: Operating System :: OS Independent
Classifier: Programming Language :: Python
Classifier: Programming Language :: Python :: 3
Classifier: Programming Language :: Python :: 3.8
Classifier: Programming Language :: Python :: 3.9
Classifier: Programming Language :: Python :: 3.10
Classifier: Programming Language :: Python :: 3.11
Classifier: Programming Language :: Python :: 3 :: Only
Classifier: Topic :: Software Development :: Libraries :: Python Modules
License-File: LICENSE
Requires-Dist: requests
Requires-Dist: requests-oauthlib
